spike_handling/__init__.py
spike_handling/cluster.py
spike_handling/cluster_exceptions.py
spike_handling/get_cluster_region_labels.py
spike_handling/get_events.py
spike_handling/spike_struct.py
spike_handling/stimuli_struct.py
spike_handling/stimuli_struct_generic.py
spike_handling/stimulus_struct.py
spike_handling/waveforms.py
util/__init__.py
util/generic_functions.py
util/probe_data_loading.py
probez-0.1.0.dist-info/LICENSE
probez-0.1.0.dist-info/METADATA
probez-0.1.0.dist-info/WHEEL
probez-0.1.0.dist-info/top_level.txt
probez-0.1.0.dist-info/RECORD
