Metadata-Version: 2.1
Name: probez
Version: 0.1.0
Summary: handle spikesorting out puts
Author-email: Stephen Lenzi <stephen.lenzi@gmail.com>
License: BSD-3-Clause
Project-URL: Homepage, https://github.com/stephenlenzi/probez
Project-URL: Bug Tracker, https://github.com/stephenlenzi/probez/issues
Project-URL: Documentation, https://stephenlenzi.github.io/probez
Project-URL: Source Code, https://github.com/stephenlenzi/probez
Project-URL: User Support, https://github.com/stephenlenzi/probez/issues
Classifier: Development Status :: 2 - Pre-Alpha
Classifier: Programming Language :: Python
Classifier: Programming Language :: Python :: 3
Classifier: Programming Language :: Python :: 3.8
Classifier: Programming Language :: Python :: 3.9
Classifier: Programming Language :: Python :: 3.10
Classifier: Operating System :: OS Independent
Classifier: License :: OSI Approved :: BSD License
Requires-Python: >=3.8.0
License-File: LICENSE
Provides-Extra: dev
Requires-Dist: pytest; extra == "dev"
Requires-Dist: pytest-cov; extra == "dev"
Requires-Dist: coverage; extra == "dev"
Requires-Dist: tox; extra == "dev"
Requires-Dist: black; extra == "dev"
Requires-Dist: mypy; extra == "dev"
Requires-Dist: pre-commit; extra == "dev"
Requires-Dist: ruff; extra == "dev"
Requires-Dist: setuptools-scm; extra == "dev"
